detectr/__init__.py
detectr/cli.py
detectr/detectr.py
detectr/mlmodel.py
detectr/mvcmodel.py
detectr/mvcview.py
detectr/parser.py
detectr/piddetails.py
detectr/tracealert.py
detectr-0.0.2.dist-info/DESCRIPTION.rst
detectr-0.0.2.dist-info/METADATA
detectr-0.0.2.dist-info/RECORD
detectr-0.0.2.dist-info/WHEEL
detectr-0.0.2.dist-info/entry_points.txt
detectr-0.0.2.dist-info/metadata.json
detectr-0.0.2.dist-info/top_level.txt
