Metadata-Version: 2.0
Name: detectr
Version: 0.0.2
Summary: Intrusion detection based on system calls.
Home-page: https://github.com/daniel-e/detectr
Author: Daniel Etzold
Author-email: detzold@gmail.com
License: MIT license
Keywords: detectr
Platform: UNKNOWN
Classifier: Development Status :: 2 - Pre-Alpha
Classifier: Intended Audience :: Developers
Classifier: License :: OSI Approved :: MIT License
Classifier: Natural Language :: English
Classifier: Programming Language :: Python :: 3
Classifier: Programming Language :: Python :: 3.5
Classifier: Programming Language :: Python :: 3.6
Classifier: Programming Language :: Python :: 3.7
Classifier: Programming Language :: Python :: 3.8
Requires-Python: >=3.5
